mudata/__init__.py
mudata/_version.py
mudata/version.py
mudata/_core/__init__.py
mudata/_core/compat.py
mudata/_core/config.py
mudata/_core/file_backing.py
mudata/_core/io.py
mudata/_core/merge.py
mudata/_core/mudata.py
mudata/_core/repr.py
mudata/_core/to_.py
mudata/_core/utils.py
mudata/_core/views.py
mudata-0.3.3.dist-info/METADATA
mudata-0.3.3.dist-info/WHEEL
mudata-0.3.3.dist-info/licenses/LICENSE
mudata-0.3.3.dist-info/RECORD
