Metadata-Version: 2.4
Name: mudata
Version: 0.3.3
Summary: Multimodal data
Project-URL: Documentation, https://mudata.readthedocs.io/
Project-URL: Homepage, https://muons.scverse.org
Project-URL: Source, https://github.com/scverse/mudata
Author: Danila Bredikhin
Maintainer-email: Danila Bredikhin <danila@stanford.edu>, Ilia Kats <i.kats@dkfz-heidelberg.de>
License: BSD 3-Clause License
License-File: LICENSE
Classifier: Intended Audience :: Science/Research
Classifier: License :: OSI Approved :: BSD License
Classifier: Operating System :: OS Independent
Classifier: Programming Language :: Python :: 3 :: Only
Classifier: Programming Language :: Python :: 3.10
Classifier: Programming Language :: Python :: 3.11
Classifier: Programming Language :: Python :: 3.12
Classifier: Programming Language :: Python :: 3.13
Classifier: Programming Language :: Python :: 3.14
Classifier: Topic :: Scientific/Engineering :: Bio-Informatics
Requires-Python: >=3.10
Requires-Dist: anndata>=0.10.8
Requires-Dist: numpy
Requires-Dist: pandas>=1.4
Requires-Dist: scipy
Requires-Dist: session-info2
